datafaser/__init__.py
datafaser/__main__.py
datafaser/data_tree.py
datafaser/files.py
datafaser/main.py
datafaser/run.py
datafaser/start.py
datafaser/validation.py
datafaser/data/schema.json
datafaser/formats/__init__.py
datafaser/formats/csv.py
datafaser/formats/json.py
datafaser/formats/text.py
datafaser/formats/xml.py
datafaser/formats/yaml.py
datafaser/operations/__init__.py
datafaser/operations/change.py
datafaser/operations/each.py
datafaser/operations/fill.py
datafaser/operations/load.py
datafaser/operations/table.py
datafaser-0.2.0.dist-info/DESCRIPTION.rst
datafaser-0.2.0.dist-info/METADATA
datafaser-0.2.0.dist-info/RECORD
datafaser-0.2.0.dist-info/WHEEL
datafaser-0.2.0.dist-info/entry_points.txt
datafaser-0.2.0.dist-info/metadata.json
datafaser-0.2.0.dist-info/top_level.txt
