Metadata-Version: 2.0
Name: datafaser
Version: 0.2.0
Summary: Data combiner and converter
Home-page: https://github.com/korpiq/python-datafaser
Author: Kalle Hallivuori
Author-email: korpiq@iki.fi
License: MIT
Keywords: data conversion
Platform: UNKNOWN
Classifier: Development Status :: 2 - Pre-Alpha
Classifier: Intended Audience :: Developers
Classifier: Topic :: Software Development :: Interpreters
Classifier: Topic :: Text Processing :: Markup
Classifier: License :: OSI Approved :: MIT License
Classifier: Programming Language :: Python :: 3.6
Requires-Dist: jsonschema (>=2.5.1)
Requires-Dist: PyYAML (>=3.11)
Requires-Dist: jinja2 (>=2.6)
Provides-Extra: dev
Provides-Extra: test
Requires-Dist: nose; extra == 'test'
Requires-Dist: nose-cov (>=1.6); extra == 'test'
